Design.v
`timescale 1ns / 1ps
//////////////////////////////////////////////////////////////////////////////////
// Company: 
// Engineer: 
// 
// Create Date: 25.04.2026 09:09:57
// Design Name: 
// Module Name: dCounter
// Project Name: 
// Target Devices: 
// Tool Versions: 
// Description: 
// 
// Dependencies: 
// 
// Revision:
// Revision 0.01 - File Created
// Additional Comments:
// 
//////////////////////////////////////////////////////////////////////////////////


module dCounter(
   input preset_i, 
   input rst_i, 
   input clk_i, 
   output reg [3:0]dout_o
);

always@(posedge clk_i, posedge rst_i) begin
   if(rst_i) begin
      dout_o <= 4'b0000;
   end
   else if(preset_i) begin
      dout_o <= 4'b0101;
   end
   else if(dout_o == 4'b1001) begin
      dout_o <= 4'b0000;
   end
   else begin
      dout_o <= dout_o + 1;
   end
end

endmodule

Testbench.v
`timescale 1ns / 1ps
//////////////////////////////////////////////////////////////////////////////////
// Company: 
// Engineer: 
// 
// Create Date: 25.04.2026 09:10:27
// Design Name: 
// Module Name: tb_dCounter
// Project Name: 
// Target Devices: 
// Tool Versions: 
// Description: 
// 
// Dependencies: 
// 
// Revision:
// Revision 0.01 - File Created
// Additional Comments:
// 
//////////////////////////////////////////////////////////////////////////////////


module tb_dCounter();
reg preset_ti;
reg rst_ti;
reg clk_ti;
wire [3:0]dout_to;

dCounter DUT(.rst_i(rst_ti), 
   .preset_i(preset_ti), 
   .clk_i(clk_ti), 
   .dout_o(dout_to));

//Clock
initial begin
   clk_ti = 1'b0;
   forever 
      #5 clk_ti = ~clk_ti;
end

//Reset
initial begin
rst_ti = 1'b1; preset_ti = 1'b0; //Reset HIGH, Preset LOW
#10 rst_ti = 1'b0; 
#150 rst_ti = 1'b1; //Reset is independent of clock? 
#25 rst_ti = 1'b0; 
#5 preset_ti = 1'b1; //Preset is dependent of clock?
#25 preset_ti = 1'b0;
#50 $finish;
end

//Capture
initial begin
$monitor("Time: %0t | Reset: %b, Clock: %b | Count: %d", $time, rst_ti, clk_ti, dout_to);
$dumpfile("dCounter.vcd");
$dumpvars(0, tb_dCounter);
end

endmodule

dCounter.vcd
$date
   Sat Apr 25 09:59:52 2026
$end

$version
  2025.2
  $dumpfile ("dCounter.vcd") 
$end

$timescale
  1ps
$end

$scope module tb_dCounter $end
$var reg 1 ! preset_ti $end
$var reg 1 " rst_ti $end
$var reg 1 # clk_ti $end
$var wire 4 $ dout_to [3:0] $end
$scope module DUT $end
$var wire 1 % preset_i $end
$var wire 1 & rst_i $end
$var wire 1 ' clk_i $end
$var reg 4 ( dout_o [3:0] $end
$upscope $end
$upscope $end
$enddefinitions $end

#0
$dumpvars
0!
1"
0#
b0 $
0%
1&
0'
b0 (
$end

#5000
1#
1'

#10000
0"
0#
0&
0'

#15000
1#
b1 $
1'
b1 (

#20000
0#
0'

#25000
1#
b10 $
1'
b10 (

#30000
0#
0'

#35000
1#
b11 $
1'
b11 (

#40000
0#
0'

#45000
1#
b100 $
1'
b100 (

#50000
0#
0'

#55000
1#
b101 $
1'
b101 (

#60000
0#
0'

#65000
1#
b110 $
1'
b110 (

#70000
0#
0'

#75000
1#
b111 $
1'
b111 (

#80000
0#
0'

#85000
1#
b1000 $
1'
b1000 (

#90000
0#
0'

#95000
1#
b1001 $
1'
b1001 (

#100000
0#
0'

#105000
1#
b0 $
1'
b0 (

#110000
0#
0'

#115000
1#
b1 $
1'
b1 (

#120000
0#
0'

#125000
1#
b10 $
1'
b10 (

#130000
0#
0'

#135000
1#
b11 $
1'
b11 (

#140000
0#
0'

#145000
1#
b100 $
1'
b100 (

#150000
0#
0'

#155000
1#
b101 $
1'
b101 (

#160000
1"
0#
b0 $
1&
0'
b0 (

#165000
1#
1'

#170000
0#
0'

#175000
1#
1'

#180000
0#
0'

#185000
0"
1#
b1 $
0&
1'
b1 (

#190000
1!
0#
1%
0'

#195000
1#
b101 $
1'
b101 (

#200000
0#
0'

#205000
1#
1'

#210000
0#
0'

#215000
0!
1#
b110 $
0%
1'
b110 (

#220000
0#
0'

#225000
1#
b111 $
1'
b111 (

#230000
0#
0'

#235000
1#
b1000 $
1'
b1000 (

#240000
0#
0'

#245000
1#
b1001 $
1'
b1001 (

#250000
0#
0'

#255000
1#
b0 $
1'
b0 (

